tracardi_string_splitter/plugin.py
tracardi_string_splitter/model/model.py
tracardi_string_splitter/model/__pycache__/model.cpython-38.pyc
tracardi_string_spliter-0.1.dist-info/LICENSE.md
tracardi_string_spliter-0.1.dist-info/METADATA
tracardi_string_spliter-0.1.dist-info/WHEEL
tracardi_string_spliter-0.1.dist-info/top_level.txt
tracardi_string_spliter-0.1.dist-info/RECORD
