Metadata-Version: 2.1
Name: tracardi-string-spliter
Version: 0.1
Summary: The purpose of this plugin is split any string
Home-page: UNKNOWN
Author: Bartosz Dobrosielski`
Author-email: bdobrosielski@edu.cdv.pl
License: UNKNOWN
Keywords: tracardi,plugin
Platform: UNKNOWN
Classifier: Programming Language :: Python :: 3
Classifier: License :: OSI Approved :: MIT License
Classifier: Operating System :: OS Independent
Requires-Python: >=3.8
License-File: LICENSE.md
Requires-Dist: tracardi-plugin-sdk
